stackmanager/__init__.py
stackmanager/cli.py
stackmanager/config.py
stackmanager/exceptions.py
stackmanager/loader.py
stackmanager/messages.py
stackmanager/packager.py
stackmanager/runner.py
stackmanager/status.py
stackmanager/uploader.py
stackmanager-1.6.1.dist-info/licenses/LICENSE
stackmanager-1.6.1.dist-info/METADATA
stackmanager-1.6.1.dist-info/WHEEL
stackmanager-1.6.1.dist-info/entry_points.txt
stackmanager-1.6.1.dist-info/top_level.txt
stackmanager-1.6.1.dist-info/RECORD
