Metadata-Version: 2.4
Name: stackmanager
Version: 1.6.1
Summary: Utility to manage CloudFormation stacks using YAML configuration file
Home-page: https://github.com/LeadingEDJE/stackmanager
Author: Andrew May
Classifier: Programming Language :: Python :: 3
Classifier: License :: OSI Approved :: MIT License
Classifier: Operating System :: OS Independent
License-File: LICENSE
Requires-Dist: Click
Requires-Dist: boto3
Requires-Dist: pyyaml
Requires-Dist: tabulate
Requires-Dist: jinja2
Requires-Dist: aws-lambda-builders>=1.30.0
Requires-Dist: arrow
Dynamic: author
Dynamic: classifier
Dynamic: description
Dynamic: description-content-type
Dynamic: home-page
Dynamic: license-file
Dynamic: requires-dist
Dynamic: summary
